MANIFEST.in
parallelprogress.py
setup.py
parallelprogress.egg-info/PKG-INFO
parallelprogress.egg-info/SOURCES.txt
parallelprogress.egg-info/dependency_links.txt
parallelprogress.egg-info/pbr.json
parallelprogress.egg-info/top_level.txt