Metadata-Version: 1.0
Name: parallelprogress
Version: 0.1.2
Summary: Share a progress bar between parallel processes
Home-page: http://github.com/aaren/parallelprogress
Author: Aaron O'Leary
Author-email: dev@aaren.me
License: UNKNOWN
Platform: UNKNOWN
